jirafts/__init__.py
jirafts/cli.py
jirafts/db.py
jirafts/downloader.py
jirafts/fields.py
jirafts/issue.py
jirafts/searcher.py
jirafts/utils.py
jirafts-0.1.0.dist-info/LICENSE
jirafts-0.1.0.dist-info/METADATA
jirafts-0.1.0.dist-info/WHEEL
jirafts-0.1.0.dist-info/entry_points.txt
jirafts-0.1.0.dist-info/top_level.txt
jirafts-0.1.0.dist-info/RECORD
