Metadata-Version: 2.1
Name: jirafts
Version: 0.1.0
Summary: Tool for searching in local copy of JIRA issues
Home-page: https://github.com/reclosedev/jirafts/
Author: Roman Haritonov
Author-email: reclosedev@gmail.com
License: MIT
Platform: UNKNOWN
Classifier: Development Status :: 4 - Beta
Classifier: Environment :: Web Environment
Classifier: License :: OSI Approved :: MIT License
Classifier: Programming Language :: Python :: 3
Classifier: Programming Language :: Python :: Implementation :: CPython
Classifier: Programming Language :: Python :: Implementation :: PyPy
Requires-Dist: html2text (>=2018.1.9)
Requires-Dist: requests (>=2.21.0)
Requires-Dist: Whoosh (>=2.7.4)
Requires-Dist: xmltodict (>=0.12.0)
Requires-Dist: peewee (>=3.9.3)
